LICENSE
MANIFEST.in
README.rst
setup.py
google/__init__.py
google/cloud/__init__.py
google/cloud/proto/__init__.py
google/cloud/proto/spanner/__init__.py
google/cloud/proto/spanner/v1/__init__.py
google/cloud/proto/spanner/v1/keys_pb2.py
google/cloud/proto/spanner/v1/keys_pb2_grpc.py
google/cloud/proto/spanner/v1/mutation_pb2.py
google/cloud/proto/spanner/v1/mutation_pb2_grpc.py
google/cloud/proto/spanner/v1/query_plan_pb2.py
google/cloud/proto/spanner/v1/query_plan_pb2_grpc.py
google/cloud/proto/spanner/v1/result_set_pb2.py
google/cloud/proto/spanner/v1/result_set_pb2_grpc.py
google/cloud/proto/spanner/v1/spanner_pb2.py
google/cloud/proto/spanner/v1/spanner_pb2_grpc.py
google/cloud/proto/spanner/v1/transaction_pb2.py
google/cloud/proto/spanner/v1/transaction_pb2_grpc.py
google/cloud/proto/spanner/v1/type_pb2.py
google/cloud/proto/spanner/v1/type_pb2_grpc.py
proto_google_cloud_spanner_v1.egg-info/PKG-INFO
proto_google_cloud_spanner_v1.egg-info/SOURCES.txt
proto_google_cloud_spanner_v1.egg-info/dependency_links.txt
proto_google_cloud_spanner_v1.egg-info/namespace_packages.txt
proto_google_cloud_spanner_v1.egg-info/requires.txt
proto_google_cloud_spanner_v1.egg-info/top_level.txt